fargatespawner/__init__.py
fargatespawner/fargatespawner.py
fargatespawner-0.0.25.dist-info/LICENSE
fargatespawner-0.0.25.dist-info/METADATA
fargatespawner-0.0.25.dist-info/WHEEL
fargatespawner-0.0.25.dist-info/top_level.txt
fargatespawner-0.0.25.dist-info/RECORD
